dynfilters/__init__.py
dynfilters/admin.py
dynfilters/apps.py
dynfilters/clone.py
dynfilters/filters.py
dynfilters/forms.py
dynfilters/model_helpers.py
dynfilters/models.py
dynfilters/shunting_yard.py
dynfilters/tests.py
dynfilters/url_helpers.py
dynfilters/urls.py
dynfilters/utils.py
dynfilters/views.py
dynfilters/migrations/0001_initial.py
dynfilters/migrations/0002_alter_dynamicfilterexpr_model.py
dynfilters/migrations/0003_alter_dynamicfilterexpr_name.py
dynfilters/migrations/0004_alter_dynamicfilterexpr_is_global_and_more.py
dynfilters/migrations/0005_alter_dynamicfilterexpr_is_global.py
dynfilters/migrations/0006_alter_dynamicfilterexpr_is_global.py
dynfilters/migrations/__init__.py
dynfilters/static/img/dynfilters/icon-share.svg
dynfilters/static/img/dynfilters/icon-viewlink.svg
dynfilters/templates/dynfilters/dynamic_filter.html
django_dynamic_filters-2.4.dist-info/LICENSE
django_dynamic_filters-2.4.dist-info/METADATA
django_dynamic_filters-2.4.dist-info/WHEEL
django_dynamic_filters-2.4.dist-info/top_level.txt
django_dynamic_filters-2.4.dist-info/RECORD
