Metadata-Version: 2.1
Name: django-dynamic-filters
Version: 2.4
Summary: A Django application for dynamic admin filters.
Home-page: https://github.com/caramdache/django-dynamic-filters
Author: Caram Dache
Author-email: caramdache@gmail.com
License: MIT
Keywords: django-admin admin dynamic filters custom query
Classifier: Environment :: Web Environment
Classifier: Framework :: Django
Classifier: Framework :: Django :: 4.0
Classifier: Intended Audience :: Developers
Classifier: License :: OSI Approved :: BSD License
Classifier: Operating System :: OS Independent
Classifier: Programming Language :: Python
Classifier: Programming Language :: Python :: 3
Classifier: Programming Language :: Python :: 3 :: Only
Classifier: Programming Language :: Python :: 3.8
Classifier: Programming Language :: Python :: 3.9
Classifier: Programming Language :: Python :: 3.10
Classifier: Topic :: Internet :: WWW/HTTP
Classifier: Topic :: Internet :: WWW/HTTP :: Dynamic Content
Requires-Python: >=3.9
License-File: LICENSE
Requires-Dist: Django (>=4.0)
Requires-Dist: furl (>=2.1)
Requires-Dist: django-admin-sortable2 (>=2.0)
